LICENSE.md
MANIFEST.in
README.md
requirements.txt
setup.cfg
setup.py
assertionchain/__init__.py
assertionchain/assertionchain.py
assertionchain.egg-info/PKG-INFO
assertionchain.egg-info/SOURCES.txt
assertionchain.egg-info/dependency_links.txt
assertionchain.egg-info/top_level.txt
tests/__init__.py
tests/test_assertionchain.py