Metadata-Version: 1.0
Name: assertionchain
Version: 0.1.1
Summary: Utility for chaining commands and incrementally checking the results
Home-page: https://github.com/justiniso/assertionchain
Author: Justin Iso
Author-email: justin+assertionchain@justiniso.com
License: UNKNOWN
Download-URL: https://github.com/justiniso/assertionchain/tarball/0.1.0
Platform: UNKNOWN
